pycocotools/__init__.py
pycocotools/_mask.cpython-39-x86_64-linux-gnu.so
pycocotools/coco.py
pycocotools/cocoeval.py
pycocotools/mask.py
wai.pycocotools-12.1.1.dist-info/METADATA
wai.pycocotools-12.1.1.dist-info/WHEEL
wai.pycocotools-12.1.1.dist-info/top_level.txt
wai.pycocotools-12.1.1.dist-info/RECORD
